{
  "data": {
    "article": {},
    "attachments": {},
    "author_id": "2026259002813005824",
    "conversation_id": "2030987518943138135",
    "created_at": "2026-04-10T06:20:14.000Z",
    "edit_controls": {
      "editable_until": "2026-04-10T07:20:14.000Z",
      "edits_remaining": 5,
      "is_edit_eligible": false
    },
    "edit_history_tweet_ids": [
      "2042487801959301463"
    ],
    "entities": {
      "mentions": [
        {
          "end": 14,
          "id": "1976659813863227392",
          "start": 0,
          "username": "qian_YuqianMi"
        }
      ]
    },
    "geo": {},
    "id": "2042487801959301463",
    "in_reply_to_user_id": "1976659813863227392",
    "lang": "zh",
    "note_tweet": {
      "entities": {}
    },
    "possibly_sensitive": false,
    "public_metrics": {
      "bookmark_count": 0,
      "impression_count": 0,
      "like_count": 0,
      "quote_count": 0,
      "reply_count": 0,
      "retweet_count": 0
    },
    "referenced_tweets": [
      {
        "id": "2030987518943138135",
        "type": "replied_to"
      }
    ],
    "reply_settings": "everyone",
    "text": "@qian_YuqianMi 没关系，我们这里来月经的时候都一直自慰。"
  },
  "includes": {
    "tweets": [
      {
        "article": {},
        "attachments": {},
        "author_id": "2026259002813005824",
        "conversation_id": "2030987518943138135",
        "created_at": "2026-04-10T06:20:14.000Z",
        "edit_controls": {
          "editable_until": "2026-04-10T07:20:14.000Z",
          "edits_remaining": 5,
          "is_edit_eligible": false
        },
        "edit_history_tweet_ids": [
          "2042487801959301463"
        ],
        "entities": {
          "mentions": [
            {
              "end": 14,
              "id": "1976659813863227392",
              "start": 0,
              "username": "qian_YuqianMi"
            }
          ]
        },
        "geo": {},
        "id": "2042487801959301463",
        "in_reply_to_user_id": "1976659813863227392",
        "lang": "zh",
        "note_tweet": {
          "entities": {}
        },
        "possibly_sensitive": false,
        "public_metrics": {
          "bookmark_count": 0,
          "impression_count": 0,
          "like_count": 0,
          "quote_count": 0,
          "reply_count": 0,
          "retweet_count": 0
        },
        "referenced_tweets": [
          {
            "id": "2030987518943138135",
            "type": "replied_to"
          }
        ],
        "reply_settings": "everyone",
        "text": "@qian_YuqianMi 没关系，我们这里来月经的时候都一直自慰。"
      },
      {
        "article": {},
        "attachments": {},
        "author_id": "1976659813863227392",
        "conversation_id": "2030987518943138135",
        "created_at": "2026-03-09T12:42:13.000Z",
        "edit_controls": {
          "editable_until": "2026-03-09T13:42:13.000Z",
          "edits_remaining": 5,
          "is_edit_eligible": true
        },
        "edit_history_tweet_ids": [
          "2030987518943138135"
        ],
        "entities": {
          "hashtags": [
            {
              "end": 89,
              "start": 85,
              "tag": "日常弥"
            }
          ]
        },
        "geo": {},
        "id": "2030987518943138135",
        "lang": "zh",
        "note_tweet": {
          "entities": {}
        },
        "possibly_sensitive": false,
        "public_metrics": {
          "bookmark_count": 44,
          "impression_count": 193709,
          "like_count": 857,
          "quote_count": 4,
          "reply_count": 78,
          "retweet_count": 13
        },
        "reply_settings": "everyone",
        "text": "其实我性瘾特别严重。。基本上是每天都要自慰的程度。不zw基本上是因为太累了或者头疼直接去睡了。绝对是因为抑郁症嗯（绝对不是因为抑郁症。（就是。（行。）哎好难过。我好差劲。#日常弥"
      }
    ],
    "users": [
      {
        "created_at": "2026-02-24T11:33:13.000Z",
        "description": "マレーシアの女の子です。日本語はあまり話せません😭 英語は少しだけ、中国語は大丈夫です！\n多重意識システムの方や日本の方と仲良くなれたら嬉しいです……\n現在、MDD（うつ病）、ADHD、自閉スペクトラム症と診断されています。\n（翻訳機を使っているので、変なところがあったらごめんなさい💦）",
        "id": "2026259002813005824",
        "name": "wispwood.sys",
        "profile_image_url": "https://pbs.twimg.com/profile_images/2041890255817818112/oZ2ZUU5V_normal.jpg",
        "protected": false,
        "public_metrics": {
          "followers_count": 15,
          "following_count": 92,
          "like_count": 354,
          "listed_count": 0,
          "media_count": 4,
          "tweet_count": 53
        },
        "username": "OHOHOH121121",
        "verified": false
      },
      {
        "created_at": "2025-10-10T14:43:43.000Z",
        "description": "二次元病弱系精神失常 | **重度依赖 | 双相 | switch | 喜欢画画 | 喜欢音乐 | 多意识体 | 千&YuMi | \n\n推当低能量朋友圈发！闲话很多。\n喜欢温柔可爱的人（同类互fo来）\n\n-【どれくらいの願いをかなえるだろう】\n-【どれくらいの想いが，まだ見ない明日へと届くだろう】\n\n让悲伤化作极光",
        "id": "1976659813863227392",
        "location": "失梦",
        "name": "千与千弥",
        "pinned_tweet_id": "2004939523277685108",
        "profile_image_url": "https://pbs.twimg.com/profile_images/2004485091540787200/54Alk-C-_normal.jpg",
        "protected": false,
        "public_metrics": {
          "followers_count": 1223,
          "following_count": 808,
          "like_count": 26733,
          "listed_count": 0,
          "media_count": 364,
          "tweet_count": 5270
        },
        "username": "qian_YuqianMi",
        "verified": false
      }
    ]
  }
}